[
  {
    "itemId": "adbea8f6-dbd5-4fcc-9081-698be2985ce1",
    "category": "science",
    "navigationKeyword1": "probability",
    "navigationKeyword2": "expected-value",
    "question": "Fair die expected value?",
    "correctAnswer": "3.5",
    "incorrectAnswers": [
      "3",
      "4",
      "2.5"
    ],
    "explanation": "Average of 1..6.",
    "keywords": [
      "expectation",
      "discrete"
    ],
    "source": "https://openstax.org/books/introductory-statistics/pages/4-2-probability-distribution-for-a-discrete-random-variable"
  },
  {
    "itemId": "3bcd40cd-611d-48af-809f-199c7224ac9e",
    "category": "science",
    "navigationKeyword1": "probability",
    "navigationKeyword2": "expected-value",
    "question": "Lottery ticket EV often?",
    "correctAnswer": "Negative (house edge)",
    "incorrectAnswers": [
      "Always positive",
      "Always zero",
      "Always 1"
    ],
    "explanation": "Rare jackpot still may not compensate cost.",
    "keywords": [
      "expected-value",
      "decisions"
    ],
    "source": "https://en.wikipedia.org/wiki/Expected_value"
  },
  {
    "itemId": "c862d34a-f243-4f4c-9c98-64dcdcfe9550",
    "category": "science",
    "navigationKeyword1": "probability",
    "navigationKeyword2": "expected-value",
    "question": "E[X+Y] if known expectations?",
    "correctAnswer": "E[X]+E[Y] always (finite)",
    "incorrectAnswers": [
      "E[X]E[Y]",
      "E[X]/E[Y]",
      "max(E[X],E[Y])"
    ],
    "explanation": "Linearity doesn\u2019t need independence.",
    "keywords": [
      "linearity",
      "expectation"
    ],
    "source": "https://openstax.org/books/introductory-statistics/pages/4-2-probability-distribution-for-a-discrete-random-variable"
  },
  {
    "itemId": "de4652ab-5b26-464a-a6cf-bfce69241e85",
    "category": "science",
    "navigationKeyword1": "probability",
    "navigationKeyword2": "expected-value",
    "question": "If independent, E[XY]?",
    "correctAnswer": "E[X]E[Y]",
    "incorrectAnswers": [
      "E[X]+E[Y]",
      "Var(XY)",
      "0"
    ],
    "explanation": "Covariance zero helps.",
    "keywords": [
      "independence",
      "product"
    ],
    "source": "https://openstax.org/books/introductory-statistics/pages/4-2-probability-distribution-for-a-discrete-random-variable"
  },
  {
    "itemId": "233e02a3-7e65-4b37-9069-86031b2ef2b5",
    "category": "science",
    "navigationKeyword1": "probability",
    "navigationKeyword2": "expected-value",
    "question": "Variance under aX+b?",
    "correctAnswer": "a^2 Var(X)",
    "incorrectAnswers": [
      "a Var(X)",
      "Var(X)+b",
      "a+b Var(X)"
    ],
    "explanation": "Shift doesn\u2019t change spread.",
    "keywords": [
      "variance-rules",
      "scale"
    ],
    "source": "https://openstax.org/books/introductory-statistics/pages/4-2-probability-distribution-for-a-discrete-random-variable"
  },
  {
    "itemId": "c2b3c9e2-b2e7-4e05-8328-b907fae947bb",
    "category": "science",
    "navigationKeyword1": "probability",
    "navigationKeyword2": "expected-value",
    "question": "Cov(X,Y) interpretation?",
    "correctAnswer": "Linear association tendency (not scale-free)",
    "incorrectAnswers": [
      "Always causal",
      "Same as P(X=Y)",
      "Always nonnegative"
    ],
    "explanation": "Correlation standardizes.",
    "keywords": [
      "covariance",
      "association"
    ],
    "source": "https://openstax.org/books/introductory-statistics/pages/10-3-the-correlation-coefficient-r"
  },
  {
    "itemId": "4b1d4eec-db43-45f7-a5cc-1c15c0ad4311",
    "category": "science",
    "navigationKeyword1": "probability",
    "navigationKeyword2": "expected-value",
    "question": "Tower property E[E[X|Y]]?",
    "correctAnswer": "E[X]",
    "incorrectAnswers": [
      "E[Y]",
      "0",
      "Var(X)"
    ],
    "explanation": "Law of total expectation.",
    "keywords": [
      "law-total-expectation",
      "conditional"
    ],
    "source": "https://en.wikipedia.org/wiki/Law_of_total_expectation"
  },
  {
    "itemId": "31d22f99-318c-46ae-9b6f-5121ecca9927",
    "category": "science",
    "navigationKeyword1": "probability",
    "navigationKeyword2": "expected-value",
    "question": "St. Petersburg paradox theme?",
    "correctAnswer": "Infinite expectation unrealistic without bank limits",
    "incorrectAnswers": [
      "Proves EV useless always",
      "Only discrete",
      "Only normal"
    ],
    "explanation": "Utility and truncation matter.",
    "keywords": [
      "st-petersburg",
      "paradox"
    ],
    "source": "https://en.wikipedia.org/wiki/St._Petersburg_paradox"
  },
  {
    "itemId": "05445209-0335-4db1-ab41-22863429362a",
    "category": "science",
    "navigationKeyword1": "probability",
    "navigationKeyword2": "expected-value",
    "question": "Insurance EV buyer side?",
    "correctAnswer": "Often negative premium vs payout (company profits)",
    "incorrectAnswers": [
      "Always positive for buyer",
      "Always zero",
      "Never uses probability"
    ],
    "explanation": "Risk transfer has value beyond EV.",
    "keywords": [
      "insurance",
      "utility"
    ],
    "source": "https://en.wikipedia.org/wiki/Expected_value"
  },
  {
    "itemId": "12b387fe-e97c-48cc-aa02-b675f8faa90d",
    "category": "science",
    "navigationKeyword1": "probability",
    "navigationKeyword2": "expected-value",
    "question": "Decision under risk simple rule?",
    "correctAnswer": "Compare expected utility/values",
    "incorrectAnswers": [
      "Always maximize max payoff",
      "Ignore probabilities",
      "Minimize always"
    ],
    "explanation": "Depends on risk aversion.",
    "keywords": [
      "decision-theory",
      "ev"
    ],
    "source": "https://en.wikipedia.org/wiki/Expected_utility_hypothesis"
  },
  {
    "itemId": "8090f113-80f2-405c-aa43-ec10301ccc26",
    "category": "science",
    "navigationKeyword1": "probability",
    "navigationKeyword2": "expected-value",
    "question": "Linearity for indicators?",
    "correctAnswer": "Sum of indicators expectation is sum of P(indicator=1)",
    "incorrectAnswers": [
      "Product of expectations always",
      "Always 1",
      "Never linear"
    ],
    "explanation": "Useful counting proofs.",
    "keywords": [
      "indicator",
      "linearity"
    ],
    "source": "https://en.wikipedia.org/wiki/Indicator_function"
  },
  {
    "itemId": "9f3a7250-7942-4269-aa86-89b28db7ca86",
    "category": "science",
    "navigationKeyword1": "probability",
    "navigationKeyword2": "expected-value",
    "question": "Monte Carlo estimate?",
    "correctAnswer": "Average of simulated draws approximates expectation",
    "incorrectAnswers": [
      "Always exact",
      "Only for discrete",
      "Never converges"
    ],
    "explanation": "LLN justification.",
    "keywords": [
      "monte-carlo",
      "simulation"
    ],
    "source": "https://en.wikipedia.org/wiki/Monte_Carlo_method"
  }
]
