[
  {
    "itemId": "2b660467-7657-4b04-88b0-9df62e6a1566",
    "category": "nature",
    "navigationKeyword1": "plants",
    "navigationKeyword2": "trees",
    "question": "What do deciduous trees do each year?",
    "correctAnswer": "shed all their leaves",
    "incorrectAnswers": [
      "keep needles year-round",
      "flower only once",
      "grow only in wetlands"
    ],
    "explanation": "Deciduous trees are defined by shedding their leaves annually.",
    "keywords": [
      "trees",
      "nature-plants"
    ],
    "source": "https://www.arborday.org/trees/treeguide/glossary.cfm"
  },
  {
    "itemId": "7f085595-dd2f-4992-884c-8d83d9be749b",
    "category": "nature",
    "navigationKeyword1": "plants",
    "navigationKeyword2": "trees",
    "question": "Most conifers produce their seeds in what structure?",
    "correctAnswer": "cones",
    "incorrectAnswers": [
      "pods",
      "berries",
      "tubers"
    ],
    "explanation": "Conifers are gymnosperms that usually bear their seeds in cones.",
    "keywords": [
      "trees",
      "nature-plants"
    ],
    "source": "https://www.britannica.com/plant/conifer/Strobili"
  },
  {
    "itemId": "0e586406-ffc6-4354-b713-85f04f9a3374",
    "category": "nature",
    "navigationKeyword1": "plants",
    "navigationKeyword2": "trees",
    "question": "Which tree is the classic commercial source of maple syrup?",
    "correctAnswer": "sugar maple",
    "incorrectAnswers": [
      "silver birch",
      "American beech",
      "eastern hemlock"
    ],
    "explanation": "Sugar maple sap is the traditional source used to make maple syrup.",
    "keywords": [
      "trees",
      "nature-plants"
    ],
    "source": "https://www.britannica.com/plant/sugar-maple"
  },
  {
    "itemId": "1f2488b4-30aa-4b34-ae59-b985bdcc68ff",
    "category": "nature",
    "navigationKeyword1": "plants",
    "navigationKeyword2": "trees",
    "question": "Acorns are the nuts of which kind of tree?",
    "correctAnswer": "oak",
    "incorrectAnswers": [
      "maple",
      "elm",
      "spruce"
    ],
    "explanation": "Acorns are produced by oak trees and are important food for many animals.",
    "keywords": [
      "trees",
      "nature-plants"
    ],
    "source": "https://www.fpl.fs.usda.gov/documnts/usda/amwood/247oak.pdf"
  },
  {
    "itemId": "c79c1a87-281b-4c29-aa02-d61686210118",
    "category": "nature",
    "navigationKeyword1": "plants",
    "navigationKeyword2": "trees",
    "question": "Mangroves are especially adapted to live along what kind of coast?",
    "correctAnswer": "salty or brackish coasts",
    "incorrectAnswers": [
      "frozen inland lakes",
      "dry mountain ridges",
      "desert dunes"
    ],
    "explanation": "Mangroves are salt-tolerant trees that thrive along tidal coasts and estuaries.",
    "keywords": [
      "trees",
      "nature-plants"
    ],
    "source": "https://www.britannica.com/plant/mangrove"
  },
  {
    "itemId": "8e6e452f-7a47-49a8-8bb2-36a2dd2a2619",
    "category": "nature",
    "navigationKeyword1": "plants",
    "navigationKeyword2": "trees",
    "question": "Which North American tree is known for white bark that peels in thin papery layers?",
    "correctAnswer": "paper birch",
    "incorrectAnswers": [
      "quaking aspen",
      "sycamore",
      "cottonwood"
    ],
    "explanation": "Paper birch has distinctive peeling bark that was historically used for canoes and roofing.",
    "keywords": [
      "trees",
      "nature-plants"
    ],
    "source": "https://www.britannica.com/plant/paper-birch/additional-info"
  }
]
