[
  {
    "itemId": "88879f86-9b10-42e8-963f-3d50291e2eaf",
    "category": "sports",
    "navigationKeyword1": "champions",
    "navigationKeyword2": "legends",
    "question": "Which basketball legend won six NBA titles with the Chicago Bulls and became the face of the sport in the 1990s?",
    "correctAnswer": "Michael Jordan",
    "incorrectAnswers": [
      "Magic Johnson",
      "Kobe Bryant",
      "Larry Bird"
    ],
    "explanation": "Jordan is one of the most recognized champions in sports history.",
    "keywords": [
      "champions",
      "legends",
      "jordan"
    ],
    "source": "https://www.nba.com/history"
  },
  {
    "itemId": "8d9e59cd-9751-4364-86ae-ca42e34825ca",
    "category": "sports",
    "navigationKeyword1": "champions",
    "navigationKeyword2": "legends",
    "question": "Which boxer called himself The Greatest and won Olympic gold before becoming heavyweight champion?",
    "correctAnswer": "Muhammad Ali",
    "incorrectAnswers": [
      "Mike Tyson",
      "Joe Frazier",
      "George Foreman"
    ],
    "explanation": "Ali became boxing's most famous champion and personality.",
    "keywords": [
      "champions",
      "legends",
      "ali"
    ],
    "source": "https://www.britannica.com/biography/Muhammad-Ali-boxer"
  },
  {
    "itemId": "5859691b-91a3-4e5c-bb26-be22eec44df5",
    "category": "sports",
    "navigationKeyword1": "champions",
    "navigationKeyword2": "legends",
    "question": "Which swimmer became the most decorated Olympian ever?",
    "correctAnswer": "Michael Phelps",
    "incorrectAnswers": [
      "Mark Spitz",
      "Ian Thorpe",
      "Caeleb Dressel"
    ],
    "explanation": "Phelps won more Olympic medals than any other athlete.",
    "keywords": [
      "champions",
      "legends",
      "phelps"
    ],
    "source": "https://www.britannica.com/biography/Michael-Phelps"
  },
  {
    "itemId": "87c5ffe1-de71-4c0a-a2b1-4ba9945b15ef",
    "category": "sports",
    "navigationKeyword1": "champions",
    "navigationKeyword2": "legends",
    "question": "Which soccer star won the 1986 World Cup and is often grouped with Pele and Messi in greatest-ever debates?",
    "correctAnswer": "Diego Maradona",
    "incorrectAnswers": [
      "Zinedine Zidane",
      "Cristiano Ronaldo",
      "Ronaldinho"
    ],
    "explanation": "Maradona's peak made him one of football's defining legends.",
    "keywords": [
      "champions",
      "legends",
      "maradona"
    ],
    "source": "https://www.britannica.com/biography/Diego-Maradona"
  },
  {
    "itemId": "67dad1cc-cf7b-439b-b852-5c294260d641",
    "category": "sports",
    "navigationKeyword1": "champions",
    "navigationKeyword2": "legends",
    "question": "Which golfer won 18 men's majors and is known as the Golden Bear?",
    "correctAnswer": "Jack Nicklaus",
    "incorrectAnswers": [
      "Tiger Woods",
      "Arnold Palmer",
      "Gary Player"
    ],
    "explanation": "Nicklaus remains the benchmark for men's major titles.",
    "keywords": [
      "champions",
      "legends",
      "nicklaus"
    ],
    "source": "https://www.britannica.com/biography/Jack-Nicklaus"
  },
  {
    "itemId": "e695df26-8f2c-4398-a9f6-e51f6e75f23e",
    "category": "sports",
    "navigationKeyword1": "champions",
    "navigationKeyword2": "legends",
    "question": "Which hockey icon holds the NHL records for goals, assists, and points?",
    "correctAnswer": "Wayne Gretzky",
    "incorrectAnswers": [
      "Mario Lemieux",
      "Gordie Howe",
      "Sidney Crosby"
    ],
    "explanation": "Gretzky's records are central to his legendary status.",
    "keywords": [
      "champions",
      "legends",
      "gretzky"
    ],
    "source": "https://www.britannica.com/sports/ice-hockey"
  },
  {
    "itemId": "e3875dee-8c6f-44b5-81cf-57f33ba422ea",
    "category": "sports",
    "navigationKeyword1": "champions",
    "navigationKeyword2": "legends",
    "question": "Which tennis star won 23 Open Era singles majors and dominated multiple decades?",
    "correctAnswer": "Serena Williams",
    "incorrectAnswers": [
      "Steffi Graf",
      "Martina Navratilova",
      "Venus Williams"
    ],
    "explanation": "Serena's longevity and major count made her a modern legend.",
    "keywords": [
      "champions",
      "legends",
      "serena"
    ],
    "source": "https://www.britannica.com/biography/Serena-Williams"
  },
  {
    "itemId": "70d9680f-6d03-48c2-a7c6-275671bfbb2f",
    "category": "sports",
    "navigationKeyword1": "champions",
    "navigationKeyword2": "legends",
    "question": "Which NFL quarterback won seven Super Bowls?",
    "correctAnswer": "Tom Brady",
    "incorrectAnswers": [
      "Joe Montana",
      "Peyton Manning",
      "Patrick Mahomes"
    ],
    "explanation": "Brady's championship record defines his place in football history.",
    "keywords": [
      "champions",
      "legends",
      "brady"
    ],
    "source": "https://www.britannica.com/biography/Tom-Brady"
  },
  {
    "itemId": "8116daa5-745c-4717-b44c-1d3df33590dd",
    "category": "sports",
    "navigationKeyword1": "champions",
    "navigationKeyword2": "legends",
    "question": "Which sprinter became famous worldwide for Olympic and world titles in the 100m and 200m?",
    "correctAnswer": "Usain Bolt",
    "incorrectAnswers": [
      "Yohan Blake",
      "Justin Gatlin",
      "Tyson Gay"
    ],
    "explanation": "Bolt's speed and personality made him a global sports legend.",
    "keywords": [
      "champions",
      "legends",
      "bolt"
    ],
    "source": "https://www.britannica.com/biography/Usain-Bolt"
  },
  {
    "itemId": "c5f26495-e6e1-4e62-9a7f-b7d815da794d",
    "category": "sports",
    "navigationKeyword1": "champions",
    "navigationKeyword2": "legends",
    "question": "Which baseball great was known as the Sultan of Swat?",
    "correctAnswer": "Babe Ruth",
    "incorrectAnswers": [
      "Lou Gehrig",
      "Joe DiMaggio",
      "Ted Williams"
    ],
    "explanation": "Ruth became the first superstar slugger of the modern game.",
    "keywords": [
      "champions",
      "legends",
      "ruth"
    ],
    "source": "https://www.britannica.com/biography/Babe-Ruth"
  },
  {
    "itemId": "48712a41-7507-48a7-8dbc-d09a2d732a95",
    "category": "sports",
    "navigationKeyword1": "champions",
    "navigationKeyword2": "legends",
    "question": "Which swimmer owns 23 Olympic gold medals and more total Olympic medals than any athlete in history?",
    "correctAnswer": "Michael Phelps",
    "incorrectAnswers": [
      "Mark Spitz",
      "Ian Thorpe",
      "Ryan Lochte"
    ],
    "explanation": "Phelps turned medal counting into a personal hobby.",
    "keywords": [
      "olympics",
      "records",
      "usa"
    ],
    "source": "https://www.olympics.com/en/athletes/michael-phelps-ii"
  },
  {
    "itemId": "e0d2a875-7be8-4b2f-8679-12a0e0037fce",
    "category": "sports",
    "navigationKeyword1": "champions",
    "navigationKeyword2": "legends",
    "question": "Which sprinter completed three consecutive Olympic sprint doubles in the 100m and 200m?",
    "correctAnswer": "Usain Bolt",
    "incorrectAnswers": [
      "Carl Lewis",
      "Yohan Blake",
      "Noah Lyles"
    ],
    "explanation": "That run of Olympic dominance is one reason Bolt became a global icon.",
    "keywords": [
      "sprinting",
      "jamaica",
      "olympics"
    ],
    "source": "https://www.olympics.com/en/athletes/usain-bolt"
  },
  {
    "itemId": "82879eeb-cf09-4f01-be09-cdbf805a2953",
    "category": "sports",
    "navigationKeyword1": "champions",
    "navigationKeyword2": "legends",
    "question": "Which tennis superstar won 23 Grand Slam singles titles and four Olympic gold medals?",
    "correctAnswer": "Serena Williams",
    "incorrectAnswers": [
      "Steffi Graf",
      "Martina Navratilova",
      "Venus Williams"
    ],
    "explanation": "Her singles dominance and Olympic success made her one of the sport's defining figures.",
    "keywords": [
      "grand-slam",
      "olympics",
      "usa"
    ],
    "source": "https://www.olympics.com/en/athletes/serena-williams"
  },
  {
    "itemId": "d946a0da-6be6-40c8-a3e9-2fd108eb26d8",
    "category": "sports",
    "navigationKeyword1": "champions",
    "navigationKeyword2": "legends",
    "question": "Which gymnast became the first to earn a perfect 10 at the Olympic Games at age 14?",
    "correctAnswer": "Nadia Comaneci",
    "incorrectAnswers": [
      "Simone Biles",
      "Olga Korbut",
      "Mary Lou Retton"
    ],
    "explanation": "Her perfect score in Montreal became one of the sport's most famous moments.",
    "keywords": [
      "olympics",
      "perfect-10",
      "romania"
    ],
    "source": "https://www.olympics.com/en/athletes/nadia-comaneci"
  },
  {
    "itemId": "3a38eea7-37b2-4d07-b846-eb2efdefb1a2",
    "category": "sports",
    "navigationKeyword1": "champions",
    "navigationKeyword2": "legends",
    "question": "Which American track star won four gold medals at the 1936 Berlin Olympics?",
    "correctAnswer": "Jesse Owens",
    "incorrectAnswers": [
      "Carl Lewis",
      "Al Oerter",
      "Bob Beamon"
    ],
    "explanation": "Owens delivered one of the most famous performances in Olympic history.",
    "keywords": [
      "berlin-1936",
      "olympics",
      "usa"
    ],
    "source": "https://www.olympics.com/en/athletes/jesse-owens"
  },
  {
    "itemId": "edbac079-33da-4980-b2de-03f3d61ba23f",
    "category": "sports",
    "navigationKeyword1": "champions",
    "navigationKeyword2": "legends",
    "question": "Which swimmer won seven gold medals at the 1972 Munich Olympics, all in world-record time?",
    "correctAnswer": "Mark Spitz",
    "incorrectAnswers": [
      "Matt Biondi",
      "Michael Phelps",
      "Caeleb Dressel"
    ],
    "explanation": "Before Phelps, Spitz's Munich haul was the gold-medal benchmark.",
    "keywords": [
      "munich-1972",
      "records",
      "swimming"
    ],
    "source": "https://www.olympics.com/en/athletes/mark-spitz"
  },
  {
    "itemId": "6e4ba938-dabd-4680-85e1-18ed1cb0aaa4",
    "category": "sports",
    "navigationKeyword1": "champions",
    "navigationKeyword2": "legends",
    "question": "Which boxing legend won Olympic light heavyweight gold in 1960 while still competing as Cassius Clay?",
    "correctAnswer": "Muhammad Ali",
    "incorrectAnswers": [
      "Joe Frazier",
      "George Foreman",
      "Sugar Ray Leonard"
    ],
    "explanation": "Ali's Olympic title came just before he transformed boxing history as a pro.",
    "keywords": [
      "boxing",
      "rome-1960",
      "olympics"
    ],
    "source": "https://www.olympics.com/en/athletes/muhammad-ali-2"
  },
  {
    "itemId": "27faeed2-baf7-4030-9035-8e5510973681",
    "category": "sports",
    "navigationKeyword1": "champions",
    "navigationKeyword2": "legends",
    "question": "Which U.S. star won Olympic gold in both the heptathlon and the long jump at the 1988 Seoul Games?",
    "correctAnswer": "Jackie Joyner-Kersee",
    "incorrectAnswers": [
      "Florence Griffith Joyner",
      "Gail Devers",
      "Heike Drechsler"
    ],
    "explanation": "Her range across events is a big reason many consider her one of the greatest athletes ever.",
    "keywords": [
      "heptathlon",
      "long-jump",
      "olympics"
    ],
    "source": "https://www.olympics.com/en/athletes/jackie-joyner-kersee"
  },
  {
    "itemId": "38ed94ad-6d1b-475a-adb0-ae03df00e126",
    "category": "sports",
    "navigationKeyword1": "champions",
    "navigationKeyword2": "legends",
    "question": "Which hockey icon retired with 894 goals and 2,857 points in the NHL?",
    "correctAnswer": "Wayne Gretzky",
    "incorrectAnswers": [
      "Mario Lemieux",
      "Gordie Howe",
      "Sidney Crosby"
    ],
    "explanation": "Gretzky's numbers still look slightly unreasonable, which is part of the fun.",
    "keywords": [
      "nhl",
      "records",
      "canada"
    ],
    "source": "https://www.nhl.com/news/wayne-gretzky-100-greatest-nhl-hockey-players-285574558"
  },
  {
    "itemId": "d7049f14-02be-4a7a-981e-3b0beca77fd1",
    "category": "sports",
    "navigationKeyword1": "champions",
    "navigationKeyword2": "legends",
    "question": "Which wide receiver finished his NFL career with 22,895 receiving yards and 208 total touchdowns?",
    "correctAnswer": "Jerry Rice",
    "incorrectAnswers": [
      "Randy Moss",
      "Terrell Owens",
      "Larry Fitzgerald"
    ],
    "explanation": "Rice's longevity and production made him the standard at his position.",
    "keywords": [
      "nfl",
      "receiving-records",
      "49ers"
    ],
    "source": "https://www.profootballhof.com/players/jerry-rice"
  },
  {
    "itemId": "1e4560be-287a-45ed-8222-19c60fa8e129",
    "category": "sports",
    "navigationKeyword1": "champions",
    "navigationKeyword2": "legends",
    "question": "Which basketball legend was known for the skyhook and won a record six NBA MVP awards?",
    "correctAnswer": "Kareem Abdul-Jabbar",
    "incorrectAnswers": [
      "Wilt Chamberlain",
      "Magic Johnson",
      "Tim Duncan"
    ],
    "explanation": "The skyhook was iconic, and the six MVPs speak for themselves.",
    "keywords": [
      "nba",
      "skyhook",
      "mvp"
    ],
    "source": "https://www.hoophall.com/hall-of-famers/kareem-abdul-jabbar"
  },
  {
    "itemId": "a1a26344-943c-4457-b10d-2b0d3b216cca",
    "category": "sports",
    "navigationKeyword1": "champions",
    "navigationKeyword2": "legends",
    "question": "Which footballer remains the only player to win three FIFA World Cups?",
    "correctAnswer": "Pele",
    "incorrectAnswers": [
      "Diego Maradona",
      "Lionel Messi",
      "Cafu"
    ],
    "explanation": "Winning one World Cup is history; winning three is Pele territory.",
    "keywords": [
      "fifa",
      "world-cup",
      "brazil"
    ],
    "source": "https://www.fifa.com/en/tournaments/mens/worldcup/articles/pele-three-world-cup-titles-only-player"
  }
]
