[
  {
    "itemId": "5c37b6af-5f59-444a-abc4-505d65d19cc8",
    "category": "civics",
    "navigationKeyword1": "international",
    "navigationKeyword2": "human-rights",
    "question": "When was the Universal Declaration of Human Rights adopted?",
    "correctAnswer": "1948",
    "incorrectAnswers": [
      "1776",
      "1919",
      "1969"
    ],
    "explanation": "The General Assembly adopted the UDHR on December 10, 1948, as a common standard.",
    "keywords": [
      "udhr",
      "history"
    ],
    "source": "https://www.un.org/en/about-us/universal-declaration-of-human-rights"
  },
  {
    "itemId": "6213a2a9-08ed-44b0-93bb-82d4ef5d5bab",
    "category": "civics",
    "navigationKeyword1": "international",
    "navigationKeyword2": "human-rights",
    "question": "What is the usual civic distinction between civil-political rights and economic-social rights?",
    "correctAnswer": "civil-political rights focus on liberty and participation; economic-social rights focus on basic needs and dignity",
    "incorrectAnswers": [
      "only one group is listed in any treaty",
      "economic rights never appear in UN texts",
      "civil rights apply only to corporations"
    ],
    "explanation": "International law often groups freedoms like speech with fair trials, and work or health with social protection.",
    "keywords": [
      "rights-types",
      "covenants"
    ],
    "source": "https://www.ohchr.org/en/what-are-human-rights"
  },
  {
    "itemId": "05b0372f-662e-43ff-9734-167a8e640d1c",
    "category": "civics",
    "navigationKeyword1": "international",
    "navigationKeyword2": "human-rights",
    "question": "What does non-discrimination require in human-rights teaching?",
    "correctAnswer": "equal protection of rights without bias on forbidden grounds such as race, sex, or religion",
    "incorrectAnswers": [
      "treating every situation identically even when needs differ",
      "banning all religious belief",
      "ending all courts"
    ],
    "explanation": "States must address unjustified unequal treatment while sometimes allowing reasonable measures.",
    "keywords": [
      "non-discrimination",
      "equality"
    ],
    "source": "https://www.un.org/en/about-us/universal-declaration-of-human-rights"
  },
  {
    "itemId": "89dbd902-21b3-452a-b295-3beaf8245333",
    "category": "civics",
    "navigationKeyword1": "international",
    "navigationKeyword2": "human-rights",
    "question": "What is a human-rights treaty body?",
    "correctAnswer": "an expert committee that monitors how states implement a specific treaty",
    "incorrectAnswers": [
      "a local school board",
      "a private stock exchange",
      "a military alliance only"
    ],
    "explanation": "Committees review reports and may issue guidance on compliance with treaty duties.",
    "keywords": [
      "treaty-bodies",
      "monitoring"
    ],
    "source": "https://www.ohchr.org/en/treaty-bodies"
  },
  {
    "itemId": "32781727-c3ff-405f-8994-96ea12a233f3",
    "category": "civics",
    "navigationKeyword1": "international",
    "navigationKeyword2": "human-rights",
    "question": "Why is the prohibition of torture treated as a firm rule in international norms?",
    "correctAnswer": "it is widely accepted that torture cannot be justified as lawful policy",
    "incorrectAnswers": [
      "because torture is encouraged in all emergencies",
      "because courts never review detention",
      "because asylum never exists"
    ],
    "explanation": "Core protections reject torture even when states face security pressures.",
    "keywords": [
      "torture",
      "jus-cogens"
    ],
    "source": "https://www.ohchr.org/en/instruments-mechanisms/instruments/convention-against-torture-and-other-cruel-inhuman-or-degrading-treatment-or-punishment"
  },
  {
    "itemId": "061ec278-b262-4bb2-ab38-2f0c05e679a2",
    "category": "civics",
    "navigationKeyword1": "international",
    "navigationKeyword2": "human-rights",
    "question": "What is universal jurisdiction in simplified civic terms?",
    "correctAnswer": "some serious crimes can be tried in a country even with no direct link, under limited legal rules",
    "incorrectAnswers": [
      "any court may hear any parking ticket worldwide",
      "only monarchs may prosecute",
      "international law bans all trials"
    ],
    "explanation": "Certain grave offenses may trigger cooperation and prosecution across borders where law allows.",
    "keywords": [
      "universal-jurisdiction",
      "accountability"
    ],
    "source": "https://www.britannica.com/topic/universal-jurisdiction"
  }
]
